{
    "annotations": {
      "list": [
        {
          "builtIn": 1,
          "datasource": {
            "type": "grafana",
            "uid": "-- Grafana --"
          },
          "enable": true,
          "hide": true,
          "iconColor": "rgba(0, 211, 255, 1)",
          "name": "Annotations & Alerts",
          "type": "dashboard"
        }
      ]
    },
    "editable": true,
    "fiscalYearStartMonth": 0,
    "graphTooltip": 0,
    "id": null,
    "links": [],
    "liveNow": false,
    "panels": [
      {
        "datasource": {
          "type": "prometheus",
          "uid": "ea08e7cb-bfd7-4fdf-a972-db42713e5a79"
        },
        "description": "State of IPFS network (if IPFS daemon is running on machine)",
        "fieldConfig": {
          "defaults": {
            "color": {
              "mode": "thresholds"
            },
            "mappings": [
              {
                "options": {
                  "0": {
                    "color": "dark-red",
                    "index": 0,
                    "text": "IPFS Down"
                  },
                  "1": {
                    "color": "dark-green",
                    "index": 1,
                    "text": "IPFS Up"
                  }
                },
                "type": "value"
              }
            ],
            "thresholds": {
              "mode": "absolute",
              "steps": [
                {
                  "color": "green",
                  "value": null
                },
                {
                  "color": "red",
                  "value": 80
                }
              ]
            }
          },
          "overrides": []
        },
        "gridPos": {
          "h": 8,
          "w": 12,
          "x": 0,
          "y": 0
        },
        "id": 3,
        "options": {
          "colorMode": "value",
          "graphMode": "area",
          "justifyMode": "auto",
          "orientation": "auto",
          "reduceOptions": {
            "calcs": [
              "lastNotNull"
            ],
            "fields": "",
            "values": false
          },
          "textMode": "auto"
        },
        "pluginVersion": "9.5.2",
        "targets": [
          {
            "datasource": {
              "type": "prometheus",
              "uid": "ea08e7cb-bfd7-4fdf-a972-db42713e5a79"
            },
            "editorMode": "builder",
            "expr": "ipfs_up",
            "legendFormat": "__auto",
            "range": true,
            "refId": "A"
          }
        ],
        "title": "IPFS network",
        "type": "stat"
      },
      {
        "datasource": {
          "type": "prometheus",
          "uid": "ea08e7cb-bfd7-4fdf-a972-db42713e5a79"
        },
        "fieldConfig": {
          "defaults": {
            "color": {
              "mode": "palette-classic"
            },
            "custom": {
              "axisCenteredZero": false,
              "axisColorMode": "text",
              "axisLabel": "",
              "axisPlacement": "auto",
              "barAlignment": 0,
              "drawStyle": "line",
              "fillOpacity": 0,
              "gradientMode": "none",
              "hideFrom": {
                "legend": false,
                "tooltip": false,
                "viz": false
              },
              "lineInterpolation": "linear",
              "lineWidth": 1,
              "pointSize": 5,
              "scaleDistribution": {
                "type": "linear"
              },
              "showPoints": "auto",
              "spanNulls": false,
              "stacking": {
                "group": "A",
                "mode": "none"
              },
              "thresholdsStyle": {
                "mode": "off"
              }
            },
            "mappings": [],
            "thresholds": {
              "mode": "absolute",
              "steps": [
                {
                  "color": "green",
                  "value": null
                },
                {
                  "color": "red",
                  "value": 80
                }
              ]
            }
          },
          "overrides": []
        },
        "gridPos": {
          "h": 8,
          "w": 12,
          "x": 0,
          "y": 8
        },
        "id": 2,
        "interval": "1",
        "options": {
          "legend": {
            "calcs": [],
            "displayMode": "list",
            "placement": "bottom",
            "showLegend": true
          },
          "tooltip": {
            "mode": "single",
            "sort": "none"
          }
        },
        "targets": [
          {
            "datasource": {
              "type": "prometheus",
              "uid": "ea08e7cb-bfd7-4fdf-a972-db42713e5a79"
            },
            "editorMode": "builder",
            "expr": "ipfs_blocks_size",
            "legendFormat": "__auto",
            "range": true,
            "refId": "A"
          }
        ],
        "title": "Panel Title",
        "type": "timeseries"
      },
      {
        "fieldConfig": {
          "defaults": {
            "color": {
              "mode": "palette-classic"
            },
            "custom": {
              "axisCenteredZero": false,
              "axisColorMode": "text",
              "axisLabel": "",
              "axisPlacement": "auto",
              "barAlignment": 0,
              "drawStyle": "line",
              "fillOpacity": 0,
              "gradientMode": "none",
              "hideFrom": {
                "legend": false,
                "tooltip": false,
                "viz": false
              },
              "lineInterpolation": "linear",
              "lineWidth": 1,
              "pointSize": 5,
              "scaleDistribution": {
                "type": "linear"
              },
              "showPoints": "auto",
              "spanNulls": false,
              "stacking": {
                "group": "A",
                "mode": "none"
              },
              "thresholdsStyle": {
                "mode": "off"
              }
            },
            "mappings": [],
            "thresholds": {
              "mode": "absolute",
              "steps": [
                {
                  "color": "green",
                  "value": null
                },
                {
                  "color": "red",
                  "value": 80
                }
              ]
            }
          },
          "overrides": []
        },
        "gridPos": {
          "h": 8,
          "w": 12,
          "x": 0,
          "y": 16
        },
        "id": 1,
        "options": {
          "legend": {
            "calcs": [],
            "displayMode": "list",
            "placement": "bottom",
            "showLegend": true
          },
          "tooltip": {
            "mode": "single",
            "sort": "none"
          }
        },
        "title": "Panel Title",
        "type": "timeseries"
      }
    ],
    "refresh": "",
    "schemaVersion": 38,
    "style": "dark",
    "tags": [],
    "templating": {
      "list": []
    },
    "time": {
      "from": "now-6h",
      "to": "now"
    },
    "timepicker": {},
    "timezone": "",
    "title": "IPFS Network dashboard - from API !!",
    "uid": "cf82334c-b241-4680-810d-8805f2c32a43",
    "version": 3,
    "weekStart": ""
  }